ips_common_db/__init__.py
ips_common_db/sql.py
IPS_Common_Library_DB-0.1.21.dist-info/AUTHORS
IPS_Common_Library_DB-0.1.21.dist-info/LICENSE
IPS_Common_Library_DB-0.1.21.dist-info/METADATA
IPS_Common_Library_DB-0.1.21.dist-info/WHEEL
IPS_Common_Library_DB-0.1.21.dist-info/pbr.json
IPS_Common_Library_DB-0.1.21.dist-info/top_level.txt
IPS_Common_Library_DB-0.1.21.dist-info/RECORD
